{
  "Star Stone Block": [
    {
      "Address": 8933608,
      "Number": "0102",
      "Link": "0000",
      "X": "6803",
      "Y": "7800",
      "ID": 121,
      "Behavior": 0,
      "Speed": 0,
      "Properties": "00",
      "Room": 804,
      "Ability": 0,
      "Underwater": false,
      "Flying": false,
      "Inhalable": false
    },
    {
      "Address": 8933644,
      "Number": "0103",
      "Link": "0000",
      "X": "C802",
      "Y": "3800",
      "ID": 121,
      "Behavior": 0,
      "Speed": 0,
      "Properties": "00",
      "Room": 804,
      "Ability": 0,
      "Underwater": false,
      "Flying": false,
      "Inhalable": false
    },
    {
      "Address": 8956172,
      "Number": "0006",
      "Link": "0000",
      "X": "A801",
      "Y": "2802",
      "ID": 121,
      "Behavior": 0,
      "Speed": 0,
      "Properties": "00",
      "Room": 173,
      "Ability": 0,
      "Underwater": false,
      "Flying": false,
      "Inhalable": false
    },
    {
      "Address": 8961308,
      "Number": "0002",
      "Link": "0000",
      "X": "A000",
      "Y": "8000",
      "ID": 125,
      "Behavior": 0,
      "Speed": 0,
      "Properties": "00",
      "Room": 146,
      "Ability": 0,
      "Underwater": false,
      "Flying": false,
      "Inhalable": false
    },
    {
      "Address": 8970360,
      "Number": "0004",
      "Link": "0000",
      "X": "C800",
      "Y": "1801",
      "ID": 121,
      "Behavior": 0,
      "Speed": 0,
      "Properties": "00",
      "Room": 702,
      "Ability": 0,
      "Underwater": false,
      "Flying": false,
      "Inhalable": false
    },
    {
      "Address": 8996788,
      "Number": "0005",
      "Link": "0101",
      "X": "A000",
      "Y": "2000",
      "ID": 136,
      "Behavior": 0,
      "Speed": 0,
      "Properties": "00",
      "Room": 315,
      "Ability": 0,
      "Underwater": false,
      "Flying": false,
      "Inhalable": false
    },
    {
      "Address": 8998944,
      "Number": "0001",
      "Link": "0101",
      "X": "6003",
      "Y": "2000",
      "ID": 126,
      "Behavior": 0,
      "Speed": 0,
      "Properties": "00000000000000000000000000000000000200",
      "Room": 322,
      "Ability": 0,
      "Underwater": false,
      "Flying": false,
      "Inhalable": false
    },
    {
      "Address": 9027276,
      "Number": "000B",
      "Link": "0000",
      "X": "C802",
      "Y": "F800",
      "ID": 121,
      "Behavior": 0,
      "Speed": 0,
      "Properties": "00",
      "Room": 134,
      "Ability": 0,
      "Underwater": false,
      "Flying": false,
      "Inhalable": false
    },
    {
      "Address": 9031304,
      "Number": "0004",
      "Link": "0000",
      "X": "B800",
      "Y": "8800",
      "ID": 121,
      "Behavior": 0,
      "Speed": 0,
      "Properties": "00",
      "Room": 815,
      "Ability": 0,
      "Underwater": false,
      "Flying": false,
      "Inhalable": false
    },
    {
      "Address": 9053012,
      "Number": "0003",
      "Link": "0000",
      "X": "E801",
      "Y": "1801",
      "ID": 121,
      "Behavior": 0,
      "Speed": 0,
      "Properties": "00",
      "Room": 113,
      "Ability": 0,
      "Underwater": false,
      "Flying": false,
      "Inhalable": false
    }
  ],
  "Small Button": [
    {
      "Address": 8933680,
      "Number": "0003",
      "Link": "0101",
      "X": "8800",
      "Y": "5000",
      "ID": 109,
      "Behavior": 0,
      "Speed": 0,
      "Properties": "0A000000000000000000000000000000000480",
      "Room": 804,
      "Ability": 0,
      "Underwater": false,
      "Flying": false,
      "Inhalable": false
    },
    {
      "Address": 8933716,
      "Number": "0004",
      "Link": "0201",
      "X": "2801",
      "Y": "8000",
      "ID": 109,
      "Behavior": 0,
      "Speed": 0,
      "Properties": "14000000000000000000000000000000000080",
      "Room": 804,
      "Ability": 0,
      "Underwater": false,
      "Flying": false,
      "Inhalable": false
    },
    {
      "Address": 8958500,
      "Number": "0007",
      "Link": "0201",
      "X": "7800",
      "Y": "2001",
      "ID": 109,
      "Behavior": 0,
      "Speed": 0,
      "Properties": "000000000000003C0000000000000000000800",
      "Room": 177,
      "Ability": 0,
      "Underwater": false,
      "Flying": false,
      "Inhalable": false
    },
    {
      "Address": 8961776,
      "Number": "0006",
      "Link": "0100",
      "X": "0802",
      "Y": "7000",
      "ID": 109,
      "Behavior": 0,
      "Speed": 0,
      "Properties": "00000000000000230000000000000000000800",
      "Room": 147,
      "Ability": 0,
      "Underwater": false,
      "Flying": false,
      "Inhalable": false
    },
    {
      "Address": 8965880,
      "Number": "0004",
      "Link": "0101",
      "X": "3002",
      "Y": "3001",
      "ID": 109,
      "Behavior": 0,
      "Speed": 0,
      "Properties": "00000000000000000000000000000000000800",
      "Room": 707,
      "Ability": 0,
      "Underwater": false,
      "Flying": false,
      "Inhalable": false
    },
    {
      "Address": 8966644,
      "Number": "000C",
      "Link": "0101",
      "X": "5000",
      "Y": "8001",
      "ID": 109,
      "Behavior": 0,
      "Speed": 0,
      "Properties": "00000000000000640000000000000000000000",
      "Room": 708,
      "Ability": 0,
      "Underwater": false,
      "Flying": false,
      "Inhalable": false
    },
    {
      "Address": 8967920,
      "Number": "0005",
      "Link": "0201",
      "X": "5801",
      "Y": "D001",
      "ID": 109,
      "Behavior": 0,
      "Speed": 0,
      "Properties": "00000000000000640000000000000000000000",
      "Room": 712,
      "Ability": 0,
      "Underwater": false,
      "Flying": false,
      "Inhalable": false
    },
    {
      "Address": 8969560,
      "Number": "0004",
      "Link": "0101",
      "X": "1801",
      "Y": "D001",
      "ID": 109,
      "Behavior": 0,
      "Speed": 0,
      "Properties": "00000000000000780000000000000000000000",
      "Room": 742,
      "Ability": 0,
      "Underwater": false,
      "Flying": false,
      "Inhalable": false
    },
    {
      "Address": 8975592,
      "Number": "0003",
      "Link": "0101",
      "X": "2001",
      "Y": "7002",
      "ID": 109,
      "Behavior": 0,
      "Speed": 0,
      "Properties": "00000000000000640000000000000000000000",
      "Room": 209,
      "Ability": 0,
      "Underwater": false,
      "Flying": false,
      "Inhalable": false
    },
    {
      "Address": 8980032,
      "Number": "0006",
      "Link": "0101",
      "X": "A000",
      "Y": "D000",
      "ID": 109,
      "Behavior": 0,
      "Speed": 0,
      "Properties": "000000000000003C0000000000000000000000",
      "Room": 228,
      "Ability": 0,
      "Underwater": false,
      "Flying": false,
      "Inhalable": false
    },
    {
      "Address": 8988796,
      "Number": "0002",
      "Link": "0101",
      "X": "3801",
      "Y": "9000",
      "ID": 109,
      "Behavior": 0,
      "Speed": 0,
      "Properties": "00",
      "Room": 533,
      "Ability": 0,
      "Underwater": false,
      "Flying": false,
      "Inhalable": false
    },
    {
      "Address": 8994976,
      "Number": "0002",
      "Link": "0101",
      "X": "3801",
      "Y": "9000",
      "ID": 109,
      "Behavior": 0,
      "Speed": 0,
      "Properties": "00",
      "Room": 310,
      "Ability": 0,
      "Underwater": false,
      "Flying": false,
      "Inhalable": false
    },
    {
      "Address": 9003416,
      "Number": "0003",
      "Link": "0001",
      "X": "B801",
      "Y": "4000",
      "ID": 109,
      "Behavior": 0,
      "Speed": 0,
      "Properties": "00",
      "Room": 404,
      "Ability": 0,
      "Underwater": false,
      "Flying": false,
      "Inhalable": false
    },
    {
      "Address": 9013784,
      "Number": "0005",
      "Link": "0300",
      "X": "3801",
      "Y": "8000",
      "ID": 109,
      "Behavior": 0,
      "Speed": 0,
      "Properties": "14000000000000000000000000000000000480",
      "Room": 426,
      "Ability": 0,
      "Underwater": false,
      "Flying": false,
      "Inhalable": false
    },
    {
      "Address": 9013820,
      "Number": "0006",
      "Link": "0200",
      "X": "3801",
      "Y": "4000",
      "ID": 109,
      "Behavior": 0,
      "Speed": 0,
      "Properties": "00000000000000000000000000000000000400",
      "Room": 426,
      "Ability": 0,
      "Underwater": false,
      "Flying": false,
      "Inhalable": false
    },
    {
      "Address": 9013856,
      "Number": "0007",
      "Link": "0101",
      "X": "B800",
      "Y": "4000",
      "ID": 109,
      "Behavior": 0,
      "Speed": 0,
      "Properties": "0A000000000000000000000000000000000080",
      "Room": 426,
      "Ability": 0,
      "Underwater": false,
      "Flying": false,
      "Inhalable": false
    },
    {
      "Address": 9014112,
      "Number": "0004",
      "Link": "0201",
      "X": "3800",
      "Y": "F000",
      "ID": 109,
      "Behavior": 0,
      "Speed": 0,
      "Properties": "000000000000002C0100000000000000000000",
      "Room": 427,
      "Ability": 0,
      "Underwater": false,
      "Flying": false,
      "Inhalable": false
    },
    {
      "Address": 9014148,
      "Number": "0005",
      "Link": "0101",
      "X": "A801",
      "Y": "9000",
      "ID": 109,
      "Behavior": 0,
      "Speed": 0,
      "Properties": "00000000000000780000000000000000000000",
      "Room": 427,
      "Ability": 0,
      "Underwater": false,
      "Flying": false,
      "Inhalable": false
    },
    {
      "Address": 9017748,
      "Number": "000A",
      "Link": "0101",
      "X": "3800",
      "Y": "7000",
      "ID": 109,
      "Behavior": 0,
      "Speed": 0,
      "Properties": "00000000000000870000000000000000000000",
      "Room": 511,
      "Ability": 0,
      "Underwater": false,
      "Flying": false,
      "Inhalable": false
    },
    {
      "Address": 9021136,
      "Number": "0002",
      "Link": "0101",
      "X": "5803",
      "Y": "C000",
      "ID": 109,
      "Behavior": 0,
      "Speed": 0,
      "Properties": "00000000000000640000000000000000000800",
      "Room": 527,
      "Ability": 0,
      "Underwater": false,
      "Flying": false,
      "Inhalable": false
    },
    {
      "Address": 9031376,
      "Number": "0006",
      "Link": "0201",
      "X": "3801",
      "Y": "5000",
      "ID": 109,
      "Behavior": 0,
      "Speed": 0,
      "Properties": "14000000000000000000000000000000000080",
      "Room": 815,
      "Ability": 0,
      "Underwater": false,
      "Flying": false,
      "Inhalable": false
    },
    {
      "Address": 9031412,
      "Number": "0007",
      "Link": "0101",
      "X": "A800",
      "Y": "9000",
      "ID": 109,
      "Behavior": 0,
      "Speed": 0,
      "Properties": "0A000000000000000000000000000000000080",
      "Room": 815,
      "Ability": 0,
      "Underwater": false,
      "Flying": false,
      "Inhalable": false
    },
    {
      "Address": 9032940,
      "Number": "0003",
      "Link": "0201",
      "X": "9002",
      "Y": "9000",
      "ID": 109,
      "Behavior": 0,
      "Speed": 0,
      "Properties": "00000000000000FF0000000000000000000000",
      "Room": 825,
      "Ability": 0,
      "Underwater": false,
      "Flying": false,
      "Inhalable": false
    },
    {
      "Address": 9035668,
      "Number": "0002",
      "Link": "0101",
      "X": "D801",
      "Y": "E000",
      "ID": 109,
      "Behavior": 0,
      "Speed": 0,
      "Properties": "00000000000000F00000000000000000000000",
      "Room": 831,
      "Ability": 0,
      "Underwater": false,
      "Flying": false,
      "Inhalable": false
    },
    {
      "Address": 9043804,
      "Number": "0004",
      "Link": "0101",
      "X": "B001",
      "Y": "8000",
      "ID": 109,
      "Behavior": 0,
      "Speed": 0,
      "Properties": "00000000000000780000000000000000000000",
      "Room": 611,
      "Ability": 0,
      "Underwater": false,
      "Flying": false,
      "Inhalable": false
    },
    {
      "Address": 9045504,
      "Number": "0004",
      "Link": "0501",
      "X": "4801",
      "Y": "6000",
      "ID": 109,
      "Behavior": 0,
      "Speed": 0,
      "Properties": "00000000000000C80000000000000000000000",
      "Room": 609,
      "Ability": 0,
      "Underwater": false,
      "Flying": false,
      "Inhalable": false
    },
    {
      "Address": 9045540,
      "Number": "0005",
      "Link": "0401",
      "X": "D001",
      "Y": "7000",
      "ID": 109,
      "Behavior": 0,
      "Speed": 0,
      "Properties": "00000000000000FF0000000000000000000000",
      "Room": 609,
      "Ability": 0,
      "Underwater": false,
      "Flying": false,
      "Inhalable": false
    },
    {
      "Address": 9045576,
      "Number": "0006",
      "Link": "0201",
      "X": "F002",
      "Y": "D000",
      "ID": 109,
      "Behavior": 0,
      "Speed": 0,
      "Properties": "00000000000000460000000000000000000000",
      "Room": 609,
      "Ability": 0,
      "Underwater": false,
      "Flying": false,
      "Inhalable": false
    },
    {
      "Address": 9045612,
      "Number": "0007",
      "Link": "0101",
      "X": "2804",
      "Y": "1001",
      "ID": 109,
      "Behavior": 0,
      "Speed": 0,
      "Properties": "00000000000000460000000000000000000000",
      "Room": 609,
      "Ability": 0,
      "Underwater": false,
      "Flying": false,
      "Inhalable": false
    },
    {
      "Address": 9045864,
      "Number": "000E",
      "Link": "0301",
      "X": "A803",
      "Y": "3000",
      "ID": 109,
      "Behavior": 0,
      "Speed": 0,
      "Properties": "000000000000001E0000000000000000000000",
      "Room": 609,
      "Ability": 0,
      "Underwater": false,
      "Flying": false,
      "Inhalable": false
    },
    {
      "Address": 9062904,
      "Number": "0001",
      "Link": "0101",
      "X": "5802",
      "Y": "6000",
      "ID": 109,
      "Behavior": 0,
      "Speed": 0,
      "Properties": "000000000000001E0000000000000000000000",
      "Room": 730,
      "Ability": 0,
      "Underwater": false,
      "Flying": false,
      "Inhalable": false
    },
    {
      "Address": 9065512,
      "Number": "0001",
      "Link": "0101",
      "X": "3800",
      "Y": "0001",
      "ID": 109,
      "Behavior": 0,
      "Speed": 0,
      "Properties": "000000000000003C0000000000000000000800",
      "Room": 912,
      "Ability": 0,
      "Underwater": false,
      "Flying": false,
      "Inhalable": false
    },
    {
      "Address": 9065548,
      "Number": "0002",
      "Link": "0201",
      "X": "8800",
      "Y": "3001",
      "ID": 109,
      "Behavior": 0,
      "Speed": 0,
      "Properties": "000000000000005A0000000000000000000800",
      "Room": 912,
      "Ability": 0,
      "Underwater": false,
      "Flying": false,
      "Inhalable": false
    },
    {
      "Address": 9065656,
      "Number": "0005",
      "Link": "0301",
      "X": "4800",
      "Y": "3001",
      "ID": 109,
      "Behavior": 0,
      "Speed": 0,
      "Properties": "00000000000000500000000000000000000800",
      "Room": 912,
      "Ability": 0,
      "Underwater": false,
      "Flying": false,
      "Inhalable": false
    },
    {
      "Address": 9066636,
      "Number": "0005",
      "Link": "0101",
      "X": "7800",
      "Y": "3001",
      "ID": 109,
      "Behavior": 0,
      "Speed": 0,
      "Properties": "00000000000000B40000000000000000000800",
      "Room": 916,
      "Ability": 0,
      "Underwater": false,
      "Flying": false,
      "Inhalable": false
    }
  ],
  "Stone Sliding Door": [
    {
      "Address": 8933752,
      "Number": "0005",
      "Link": "0201",
      "X": "8801",
      "Y": "5000",
      "ID": 113,
      "Behavior": 0,
      "Speed": 0,
      "Properties": "00",
      "Room": 804,
      "Ability": 0,
      "Underwater": false,
      "Flying": false,
      "Inhalable": false
    },
    {
      "Address": 8933788,
      "Number": "0006",
      "Link": "0101",
      "X": "B800",
      "Y": "5000",
      "ID": 113,
      "Behavior": 0,
      "Speed": 0,
      "Properties": "00",
      "Room": 804,
      "Ability": 0,
      "Underwater": false,
      "Flying": false,
      "Inhalable": false
    },
    {
      "Address": 8958464,
      "Number": "0006",
      "Link": "0201",
      "X": "A800",
      "Y": "2001",
      "ID": 113,
      "Behavior": 0,
      "Speed": 0,
      "Properties": "00",
      "Room": 177,
      "Ability": 0,
      "Underwater": false,
      "Flying": false,
      "Inhalable": false
    },
    {
      "Address": 8961812,
      "Number": "0007",
      "Link": "0101",
      "X": "7802",
      "Y": "7000",
      "ID": 113,
      "Behavior": 0,
      "Speed": 0,
      "Properties": "00",
      "Room": 147,
      "Ability": 0,
      "Underwater": false,
      "Flying": false,
      "Inhalable": false
    },
    {
      "Address": 8965772,
      "Number": "0002",
      "Link": "0101",
      "X": "6802",
      "Y": "3001",
      "ID": 113,
      "Behavior": 0,
      "Speed": 0,
      "Properties": "00",
      "Room": 707,
      "Ability": 0,
      "Underwater": false,
      "Flying": false,
      "Inhalable": false
    },
    {
      "Address": 8966608,
      "Number": "000B",
      "Link": "0101",
      "X": "8800",
      "Y": "8001",
      "ID": 113,
      "Behavior": 0,
      "Speed": 0,
      "Properties": "00",
      "Room": 708,
      "Ability": 0,
      "Underwater": false,
      "Flying": false,
      "Inhalable": false
    },
    {
      "Address": 8968064,
      "Number": "0008",
      "Link": "0201",
      "X": "2001",
      "Y": "A001",
      "ID": 113,
      "Behavior": 0,
      "Speed": 0,
      "Properties": "00",
      "Room": 712,
      "Ability": 0,
      "Underwater": false,
      "Flying": false,
      "Inhalable": false
    },
    {
      "Address": 8969704,
      "Number": "0008",
      "Link": "0101",
      "X": "C800",
      "Y": "D001",
      "ID": 113,
      "Behavior": 0,
      "Speed": 0,
      "Properties": "00",
      "Room": 742,
      "Ability": 0,
      "Underwater": false,
      "Flying": false,
      "Inhalable": false
    },
    {
      "Address": 8975628,
      "Number": "0004",
      "Link": "0101",
      "X": "E000",
      "Y": "6002",
      "ID": 113,
      "Behavior": 0,
      "Speed": 0,
      "Properties": "00",
      "Room": 209,
      "Ability": 0,
      "Underwater": false,
      "Flying": false,
      "Inhalable": false
    },
    {
      "Address": 8979996,
      "Number": "0005",
      "Link": "0101",
      "X": "C800",
      "Y": "9000",
      "ID": 113,
      "Behavior": 0,
      "Speed": 0,
      "Properties": "00",
      "Room": 228,
      "Ability": 0,
      "Underwater": false,
      "Flying": false,
      "Inhalable": false
    },
    {
      "Address": 8988760,
      "Number": "0001",
      "Link": "0101",
      "X": "9800",
      "Y": "8000",
      "ID": 113,
      "Behavior": 0,
      "Speed": 0,
      "Properties": "00",
      "Room": 533,
      "Ability": 0,
      "Underwater": false,
      "Flying": false,
      "Inhalable": false
    },
    {
      "Address": 8995012,
      "Number": "0003",
      "Link": "0101",
      "X": "B801",
      "Y": "9000",
      "ID": 113,
      "Behavior": 0,
      "Speed": 0,
      "Properties": "00",
      "Room": 310,
      "Ability": 0,
      "Underwater": false,
      "Flying": false,
      "Inhalable": false
    },
    {
      "Address": 9003452,
      "Number": "0004",
      "Link": "0001",
      "X": "6801",
      "Y": "5000",
      "ID": 113,
      "Behavior": 0,
      "Speed": 0,
      "Properties": "00",
      "Room": 404,
      "Ability": 0,
      "Underwater": false,
      "Flying": false,
      "Inhalable": false
    },
    {
      "Address": 9013676,
      "Number": "0002",
      "Link": "0301",
      "X": "7801",
      "Y": "4000",
      "ID": 113,
      "Behavior": 0,
      "Speed": 0,
      "Properties": "00",
      "Room": 426,
      "Ability": 0,
      "Underwater": false,
      "Flying": false,
      "Inhalable": false
    },
    {
      "Address": 9013712,
      "Number": "0003",
      "Link": "0101",
      "X": "0801",
      "Y": "4000",
      "ID": 113,
      "Behavior": 0,
      "Speed": 0,
      "Properties": "00",
      "Room": 426,
      "Ability": 0,
      "Underwater": false,
      "Flying": false,
      "Inhalable": false
    },
    {
      "Address": 9013748,
      "Number": "0004",
      "Link": "0201",
      "X": "0801",
      "Y": "8000",
      "ID": 113,
      "Behavior": 0,
      "Speed": 0,
      "Properties": "00",
      "Room": 426,
      "Ability": 0,
      "Underwater": false,
      "Flying": false,
      "Inhalable": false
    },
    {
      "Address": 9014184,
      "Number": "0006",
      "Link": "0101",
      "X": "4801",
      "Y": "1001",
      "ID": 113,
      "Behavior": 0,
      "Speed": 0,
      "Properties": "00",
      "Room": 427,
      "Ability": 0,
      "Underwater": false,
      "Flying": false,
      "Inhalable": false
    },
    {
      "Address": 9014220,
      "Number": "0007",
      "Link": "0201",
      "X": "5802",
      "Y": "F000",
      "ID": 113,
      "Behavior": 0,
      "Speed": 0,
      "Properties": "00",
      "Room": 427,
      "Ability": 0,
      "Underwater": false,
      "Flying": false,
      "Inhalable": false
    },
    {
      "Address": 9017712,
      "Number": "0009",
      "Link": "0101",
      "X": "E800",
      "Y": "9000",
      "ID": 113,
      "Behavior": 0,
      "Speed": 0,
      "Properties": "00",
      "Room": 511,
      "Ability": 0,
      "Underwater": false,
      "Flying": false,
      "Inhalable": false
    },
    {
      "Address": 9021568,
      "Number": "000E",
      "Link": "0101",
      "X": "2803",
      "Y": "9000",
      "ID": 113,
      "Behavior": 0,
      "Speed": 0,
      "Properties": "00",
      "Room": 527,
      "Ability": 0,
      "Underwater": false,
      "Flying": false,
      "Inhalable": false
    },
    {
      "Address": 9031268,
      "Number": "0003",
      "Link": "0101",
      "X": "1801",
      "Y": "5000",
      "ID": 113,
      "Behavior": 0,
      "Speed": 0,
      "Properties": "00",
      "Room": 815,
      "Ability": 0,
      "Underwater": false,
      "Flying": false,
      "Inhalable": false
    },
    {
      "Address": 9031340,
      "Number": "0005",
      "Link": "0201",
      "X": "1801",
      "Y": "9000",
      "ID": 113,
      "Behavior": 0,
      "Speed": 0,
      "Properties": "00",
      "Room": 815,
      "Ability": 0,
      "Underwater": false,
      "Flying": false,
      "Inhalable": false
    },
    {
      "Address": 9032904,
      "Number": "0002",
      "Link": "0201",
      "X": "5802",
      "Y": "7000",
      "ID": 113,
      "Behavior": 0,
      "Speed": 0,
      "Properties": "00",
      "Room": 825,
      "Ability": 0,
      "Underwater": false,
      "Flying": false,
      "Inhalable": false
    },
    {
      "Address": 9035704,
      "Number": "0003",
      "Link": "0101",
      "X": "1802",
      "Y": "1001",
      "ID": 113,
      "Behavior": 0,
      "Speed": 0,
      "Properties": "00",
      "Room": 831,
      "Ability": 0,
      "Underwater": false,
      "Flying": false,
      "Inhalable": false
    },
    {
      "Address": 9043768,
      "Number": "0003",
      "Link": "0101",
      "X": "7801",
      "Y": "8000",
      "ID": 113,
      "Behavior": 0,
      "Speed": 0,
      "Properties": "00",
      "Room": 611,
      "Ability": 0,
      "Underwater": false,
      "Flying": false,
      "Inhalable": false
    },
    {
      "Address": 9045684,
      "Number": "0009",
      "Link": "0501",
      "X": "6800",
      "Y": "7000",
      "ID": 113,
      "Behavior": 0,
      "Speed": 0,
      "Properties": "00",
      "Room": 609,
      "Ability": 0,
      "Underwater": false,
      "Flying": false,
      "Inhalable": false
    },
    {
      "Address": 9045720,
      "Number": "000A",
      "Link": "0401",
      "X": "B800",
      "Y": "7000",
      "ID": 113,
      "Behavior": 0,
      "Speed": 0,
      "Properties": "00",
      "Room": 609,
      "Ability": 0,
      "Underwater": false,
      "Flying": false,
      "Inhalable": false
    },
    {
      "Address": 9045756,
      "Number": "000B",
      "Link": "0101",
      "X": "E803",
      "Y": "1001",
      "ID": 113,
      "Behavior": 0,
      "Speed": 0,
      "Properties": "00",
      "Room": 609,
      "Ability": 0,
      "Underwater": false,
      "Flying": false,
      "Inhalable": false
    },
    {
      "Address": 9045792,
      "Number": "000C",
      "Link": "0201",
      "X": "9802",
      "Y": "A000",
      "ID": 113,
      "Behavior": 0,
      "Speed": 0,
      "Properties": "00",
      "Room": 609,
      "Ability": 0,
      "Underwater": false,
      "Flying": false,
      "Inhalable": false
    },
    {
      "Address": 9045828,
      "Number": "000D",
      "Link": "0301",
      "X": "1804",
      "Y": "3000",
      "ID": 113,
      "Behavior": 0,
      "Speed": 0,
      "Properties": "00",
      "Room": 609,
      "Ability": 0,
      "Underwater": false,
      "Flying": false,
      "Inhalable": false
    },
    {
      "Address": 9062940,
      "Number": "0002",
      "Link": "0101",
      "X": "0802",
      "Y": "8000",
      "ID": 113,
      "Behavior": 0,
      "Speed": 0,
      "Properties": "00",
      "Room": 730,
      "Ability": 0,
      "Underwater": false,
      "Flying": false,
      "Inhalable": false
    },
    {
      "Address": 9065476,
      "Number": "0000",
      "Link": "0101",
      "X": "4800",
      "Y": "0001",
      "ID": 113,
      "Behavior": 0,
      "Speed": 0,
      "Properties": "00",
      "Room": 912,
      "Ability": 0,
      "Underwater": false,
      "Flying": false,
      "Inhalable": false
    },
    {
      "Address": 9065584,
      "Number": "0003",
      "Link": "0301",
      "X": "D800",
      "Y": "0001",
      "ID": 113,
      "Behavior": 0,
      "Speed": 0,
      "Properties": "00",
      "Room": 912,
      "Ability": 0,
      "Underwater": false,
      "Flying": false,
      "Inhalable": false
    },
    {
      "Address": 9065620,
      "Number": "0004",
      "Link": "0201",
      "X": "8800",
      "Y": "0001",
      "ID": 113,
      "Behavior": 0,
      "Speed": 0,
      "Properties": "00",
      "Room": 912,
      "Ability": 0,
      "Underwater": false,
      "Flying": false,
      "Inhalable": false
    },
    {
      "Address": 9066600,
      "Number": "0004",
      "Link": "0101",
      "X": "D800",
      "Y": "3001",
      "ID": 113,
      "Behavior": 0,
      "Speed": 0,
      "Properties": "00",
      "Room": 916,
      "Ability": 0,
      "Underwater": false,
      "Flying": false,
      "Inhalable": false
    }
  ],
  "Big Switch": [
    {
      "Address": 8940000,
      "Number": "0001",
      "Link": "0D01",
      "X": "8800",
      "Y": "6000",
      "ID": 134,
      "Behavior": 0,
      "Speed": 0,
      "Properties": "00000007000000000000000000000000000600",
      "Room": 590,
      "Ability": 0,
      "Underwater": false,
      "Flying": false,
      "Inhalable": false
    },
    {
      "Address": 8947524,
      "Number": "0004",
      "Link": "0601",
      "X": "8800",
      "Y": "6000",
      "ID": 134,
      "Behavior": 0,
      "Speed": 0,
      "Properties": "00000003000000000000000000000000000600",
      "Room": 194,
      "Ability": 0,
      "Underwater": false,
      "Flying": false,
      "Inhalable": false
    },
    {
      "Address": 8959236,
      "Number": "0002",
      "Link": "0901",
      "X": "8000",
      "Y": "8000",
      "ID": 134,
      "Behavior": 0,
      "Speed": 0,
      "Properties": "00000005000000000000000000000000000600",
      "Room": 192,
      "Ability": 0,
      "Underwater": false,
      "Flying": false,
      "Inhalable": false
    },
    {
      "Address": 8967552,
      "Number": "0004",
      "Link": "0201",
      "X": "7801",
      "Y": "8001",
      "ID": 134,
      "Behavior": 0,
      "Speed": 0,
      "Properties": "00000001000000000000000000000000000600",
      "Room": 711,
      "Ability": 0,
      "Underwater": false,
      "Flying": false,
      "Inhalable": false
    },
    {
      "Address": 8970072,
      "Number": "0003",
      "Link": "0101",
      "X": "8800",
      "Y": "8000",
      "ID": 134,
      "Behavior": 0,
      "Speed": 0,
      "Properties": "00000002000000000000000000000000000600",
      "Room": 790,
      "Ability": 0,
      "Underwater": false,
      "Flying": false,
      "Inhalable": false
    },
    {
      "Address": 8982836,
      "Number": "0006",
      "Link": "0B01",
      "X": "8000",
      "Y": "8000",
      "ID": 134,
      "Behavior": 0,
      "Speed": 0,
      "Properties": "0000000B000000000000000000000000000600",
      "Room": 290,
      "Ability": 0,
      "Underwater": false,
      "Flying": false,
      "Inhalable": false
    },
    {
      "Address": 8988472,
      "Number": "0000",
      "Link": "0C01",
      "X": "8800",
      "Y": "8000",
      "ID": 134,
      "Behavior": 0,
      "Speed": 0,
      "Properties": "0000000C000000000000000000000000000600",
      "Room": 291,
      "Ability": 0,
      "Underwater": false,
      "Flying": false,
      "Inhalable": false
    },
    {
      "Address": 9000984,
      "Number": "0003",
      "Link": "0F01",
      "X": "8800",
      "Y": "5000",
      "ID": 134,
      "Behavior": 0,
      "Speed": 0,
      "Properties": "00000008000000000000000000000000000600",
      "Room": 390,
      "Ability": 0,
      "Underwater": false,
      "Flying": false,
      "Inhalable": false
    },
    {
      "Address": 9014692,
      "Number": "0003",
      "Link": "0E01",
      "X": "8800",
      "Y": "5000",
      "ID": 134,
      "Behavior": 0,
      "Speed": 0,
      "Properties": "0000000F000000000000000000000000000600",
      "Room": 490,
      "Ability": 0,
      "Underwater": false,
      "Flying": false,
      "Inhalable": false
    },
    {
      "Address": 9023972,
      "Number": "0002",
      "Link": "0501",
      "X": "8800",
      "Y": "8000",
      "ID": 134,
      "Behavior": 0,
      "Speed": 0,
      "Properties": "00000004000000000000000000000000000600",
      "Room": 591,
      "Ability": 0,
      "Underwater": false,
      "Flying": false,
      "Inhalable": false
    },
    {
      "Address": 9024228,
      "Number": "0002",
      "Link": "0301",
      "X": "8800",
      "Y": "6000",
      "ID": 134,
      "Behavior": 0,
      "Speed": 0,
      "Properties": "0000000D000000000000000000000000000600",
      "Room": 191,
      "Ability": 0,
      "Underwater": false,
      "Flying": false,
      "Inhalable": false
    },
    {
      "Address": 9036764,
      "Number": "0003",
      "Link": "0401",
      "X": "8800",
      "Y": "8000",
      "ID": 134,
      "Behavior": 0,
      "Speed": 0,
      "Properties": "0000000E000000000000000000000000000600",
      "Room": 890,
      "Ability": 0,
      "Underwater": false,
      "Flying": false,
      "Inhalable": false
    },
    {
      "Address": 9040140,
      "Number": "0003",
      "Link": "0701",
      "X": "8800",
      "Y": "6000",
      "ID": 134,
      "Behavior": 0,
      "Speed": 0,
      "Properties": "00000009000000000000000000000000000600",
      "Room": 592,
      "Ability": 0,
      "Underwater": false,
      "Flying": false,
      "Inhalable": false
    },
    {
      "Address": 9049784,
      "Number": "0002",
      "Link": "0801",
      "X": "8800",
      "Y": "8000",
      "ID": 134,
      "Behavior": 0,
      "Speed": 0,
      "Properties": "0000000A000000000000000000000000000600",
      "Room": 502,
      "Ability": 0,
      "Underwater": false,
      "Flying": false,
      "Inhalable": false
    },
    {
      "Address": 9056388,
      "Number": "0001",
      "Link": "0A01",
      "X": "8800",
      "Y": "8000",
      "ID": 134,
      "Behavior": 0,
      "Speed": 0,
      "Properties": "00000006000000000000000000000000000600",
      "Room": 600,
      "Ability": 0,
      "Underwater": false,
      "Flying": false,
      "Inhalable": false
    }
  ]
}